{
  "implementation_authority": "DA-001",
  "surface": "Design Authority",
  "infrastructure_status": "COMPLETE",
  "content_status": {
    "DA-001-DESIGN-AUTHORITY.md": "READY",
    "DA-MANIFEST.schema.yaml": "PENDING",
    "VISUAL.schema.md": "PENDING",
    "LAYOUT.schema.md": "PENDING",
    "MOTION.schema.md": "PENDING",
    "BRAND.schema.md": "PENDING",
    "AI-GENERATION.schema.md": "PENDING",
    "DESIGN-CONSTRAINTS.schema.md": "PENDING",
    "TOKENS.schema.yaml": "PENDING",
    "DESIGN-PROVENANCE.schema.md": "PENDING"
  },
  "asset_completion": {
    "completed": 1,
    "total": 10,
    "percent": 10.0
  }
}